kbase_report_state/__init__.py
kbase_report_state/__main__.py
kbase_report_state-0.0.9.dist-info/LICENSE
kbase_report_state-0.0.9.dist-info/WHEEL
kbase_report_state-0.0.9.dist-info/METADATA
kbase_report_state-0.0.9.dist-info/RECORD
