Metadata-Version: 2.1
Name: kbase_report_state
Version: 0.0.9
Summary: API to Save KBase report state.
Author-email: Dakota Blair <dblair@bnl.gov>
Requires-Python: >=3.8.2
Classifier: License :: OSI Approved :: MIT License
